bfieldtools/__init__.py
bfieldtools/coil_optimize.py
bfieldtools/contour.py
bfieldtools/flatten_mesh.py
bfieldtools/integrals.py
bfieldtools/kicad_io.py
bfieldtools/line_conductor.py
bfieldtools/line_magnetics.py
bfieldtools/mesh_calculus.py
bfieldtools/mesh_conductor.py
bfieldtools/mesh_impedance.py
bfieldtools/mesh_magnetics.py
bfieldtools/quadratures.py
bfieldtools/sphtools.py
bfieldtools/suhtools.py
bfieldtools/thermal_noise.py
bfieldtools/utils.py
bfieldtools/version.py
bfieldtools/viz.py
bfieldtools/example_meshes/10x10_plane.obj
bfieldtools/example_meshes/10x10_plane_hires.obj
bfieldtools/example_meshes/bunny_repaired.mtl
bfieldtools/example_meshes/bunny_repaired.obj
bfieldtools/example_meshes/closed_cylinder.stl
bfieldtools/example_meshes/closed_cylinder_remeshed.stl
bfieldtools/example_meshes/cube.stl
bfieldtools/example_meshes/cube_fillet.stl
bfieldtools/example_meshes/curved_surf_w_hole.stl
bfieldtools/example_meshes/cylinder.stl
bfieldtools/example_meshes/disc_extrafine.stl
bfieldtools/example_meshes/disc_extremelyfine.stl
bfieldtools/example_meshes/disc_finer.stl
bfieldtools/example_meshes/ellipsoid_cylinder_intersection.stl
bfieldtools/example_meshes/meg_helmet.obj
bfieldtools/example_meshes/open_cylinder.stl
bfieldtools/example_meshes/plane_w_holes.stl
bfieldtools/example_meshes/star.stl
bfieldtools/example_meshes/star_dense.stl
bfieldtools/example_meshes/thin_film_heater.stl
bfieldtools/example_meshes/thinspiral.obj
bfieldtools/example_meshes/unit_disc.stl
bfieldtools/example_meshes/unit_sphere.stl
bfieldtools/example_meshes/unit_spiral.stl
bfieldtools/example_meshes/unitdisc_extremelyfine.stl
bfieldtools/legacy/__init__.py
bfieldtools/legacy/integrals.py
bfieldtools/legacy/mesh_calculus.py
bfieldtools/legacy/mesh_magnetics.py
bfieldtools/legacy/mesh_properties.py
bfieldtools/legacy/sphtools.py
tests/__init__.py
tests/test_coil_optimize.py
tests/test_contour.py
tests/test_contour_basis.py
tests/test_integrals.py
tests/test_kicad_io.py
bfieldtools-0.11.3.dist-info/LICENSE.txt
bfieldtools-0.11.3.dist-info/METADATA
bfieldtools-0.11.3.dist-info/WHEEL
bfieldtools-0.11.3.dist-info/top_level.txt
bfieldtools-0.11.3.dist-info/RECORD
