Metadata-Version: 2.1
Name: bfieldtools
Version: 0.11.3
Summary: Open-source Python software for magnetic field modeling
Home-page: https://bfieldtools.github.io/
Download-URL: https://github.com/bfieldtools/bfieldtools
Maintainer: Rasmus Zetter
Maintainer-email: rasmus.zetter@aalto.fi
License: BSD (3-clause)
Platform: any
Classifier: Intended Audience :: Science/Research
Classifier: Intended Audience :: Developers
Classifier: Programming Language :: Python
Classifier: Topic :: Software Development
Classifier: Topic :: Scientific/Engineering
Requires-Python: >=3.6
License-File: LICENSE.txt
Requires-Dist: numpy
Requires-Dist: scipy
Requires-Dist: matplotlib
Requires-Dist: sip
Requires-Dist: pyvista
Requires-Dist: cvxpy (>=1.1.14)
Requires-Dist: cvxopt
Requires-Dist: trimesh
Requires-Dist: shapely
Requires-Dist: psutil
